click_app_template_demo/__init__.py
click_app_template_demo/cli.py
click_app_template_demo-0.1.dist-info/LICENSE
click_app_template_demo-0.1.dist-info/METADATA
click_app_template_demo-0.1.dist-info/WHEEL
click_app_template_demo-0.1.dist-info/entry_points.txt
click_app_template_demo-0.1.dist-info/top_level.txt
click_app_template_demo-0.1.dist-info/RECORD
