Metadata-Version: 2.1
Name: click-app-template-demo
Version: 0.1
Summary: Demonstrating https://github.com/simonw/click-app
Home-page: https://github.com/simonw/click-app-template-demo
Author: Simon Willison
License: Apache License, Version 2.0
Project-URL: Issues, https://github.com/simonw/click-app-template-demo/issues
Project-URL: CI, https://github.com/simonw/click-app-template-demo/actions
Project-URL: Changelog, https://github.com/simonw/click-app-template-demo/releases
Platform: UNKNOWN
Requires-Dist: click
Provides-Extra: test
Requires-Dist: pytest ; extra == 'test'
